{
    "intents": [
	{
	    "intent":"ReminderListIntent"
	},
	{
	    "intent": "RemindIntent",
	    "slots": [
		{
		    "name": "Drug",
		    "type": "LIST_OF_DRUGS"
		},
		{
		    "name": "Time",
		    "type": "AMAZON.TIME"
		}
	    ]
	},
        {
	    "intent": "DURIntent",
	    "slots": [
		{
		    "name": "Drug",
		    "type": "LIST_OF_DRUGS"
		}
	    ]
	},
	{
	    "intent": "AMAZON.CancelIntent"
	},
	{
	    "intent": "HowDoYouWorkIntent"
	},
	{
	    "intent": "SayReminderIntent",
	    "slots": [
		{
		    "name": "Drug",
		    "type": "LIST_OF_DRUGS"
		}
	    ]
	}
    ]
}
